setup.py
tornado_router/__init__.py
tornado_router/router.py
tornado_router.egg-info/PKG-INFO
tornado_router.egg-info/SOURCES.txt
tornado_router.egg-info/dependency_links.txt
tornado_router.egg-info/requires.txt
tornado_router.egg-info/top_level.txt