Metadata-Version: 1.1
Name: tornado-router
Version: 0.1.2
Summary: function-based router for Tornado Web Framework that supports asynchronous authentication, json request and more
Home-page: https://github.com/shicky/tornado_router
Author: Sick Yoon
Author-email: shicky@gmail.com
License: MIT
Keywords: tornado,router,asynchronous,authentication,decorator
Platform: POSIX
Classifier: License :: OSI Approved :: MIT License
Classifier: Development Status :: 3 - Alpha
Classifier: Programming Language :: Python
Classifier: Programming Language :: Python :: 3
Classifier: Programming Language :: Python :: 3.4
Classifier: Programming Language :: Python :: 3.5
Classifier: Operating System :: POSIX
Classifier: Environment :: Web Environment
Classifier: Intended Audience :: Developers
Classifier: Topic :: Software Development
Classifier: Topic :: Software Development :: Libraries
